[{"id":"osm-node-622753177","lat":33.22957,"lon":131.602195,"city":"oita","source":"osm","changingTable":false,"wheelchair":false,"fee":false},{"id":"osm-node-622880576","lat":33.236884,"lon":131.609919,"city":"oita","source":"osm","changingTable":false,"wheelchair":true,"fee":false},{"id":"osm-node-623069449","lat":33.240653,"lon":131.607668,"city":"oita","source":"osm","changingTable":false,"wheelchair":true,"fee":false},{"id":"osm-node-1921534438","lat":33.233123,"lon":131.648239,"city":"oita","source":"osm","changingTable":false,"wheelchair":false,"fee":false},{"id":"osm-node-1949360824","lat":33.228583,"lon":131.650855,"city":"oita","source":"osm","changingTable":false,"wheelchair":false,"fee":false},{"id":"osm-node-1952842299","lat":33.230193,"lon":131.647075,"city":"oita","source":"osm","changingTable":false,"wheelchair":false,"fee":false},{"id":"osm-node-1954197158","lat":33.233426,"lon":131.645431,"city":"oita","source":"osm","changingTable":false,"wheelchair":false,"fee":false},{"id":"osm-node-1962939286","lat":33.249914,"lon":131.628147,"city":"oita","source":"osm","changingTable":false,"wheelchair":false,"fee":false},{"id":"osm-node-1962939598","lat":33.252582,"lon":131.627074,"city":"oita","source":"osm","changingTable":false,"wheelchair":true,"fee":false},{"id":"osm-node-1962939704","lat":33.253559,"lon":131.624005,"city":"oita","source":"osm","changingTable":false,"wheelchair":false,"fee":false},{"id":"osm-node-1964032904","lat":33.250473,"lon":131.634207,"city":"oita","source":"osm","changingTable":false,"wheelchair":true,"fee":false},{"id":"osm-node-1964032914","lat":33.250624,"lon":131.6339,"city":"oita","source":"osm","changingTable":false,"wheelchair":true,"fee":false},{"id":"osm-node-1964032922","lat":33.250814,"lon":131.631877,"city":"oita","source":"osm","changingTable":false,"wheelchair":true,"fee":false},{"id":"osm-node-1964400074","lat":33.243379,"lon":131.652423,"city":"oita","source":"osm","changingTable":false,"wheelchair":false,"fee":false},{"id":"osm-node-2014146852","lat":33.227259,"lon":131.648145,"city":"oita","source":"osm","changingTable":false,"wheelchair":false,"fee":false},{"id":"osm-node-2014146940","lat":33.227401,"lon":131.65058,"city":"oita","source":"osm","changingTable":false,"wheelchair":false,"fee":false},{"id":"osm-node-2072997916","lat":33.237546,"lon":131.655379,"city":"oita","source":"osm","changingTable":false,"wheelchair":false,"fee":false},{"id":"osm-node-2072998709","lat":33.238253,"lon":131.653272,"city":"oita","source":"osm","changingTable":false,"wheelchair":false,"fee":false},{"id":"osm-node-2090461954","lat":33.232167,"lon":131.606953,"city":"oita","source":"osm","changingTable":false,"wheelchair":false,"fee":false},{"id":"osm-node-2090461958","lat":33.232843,"lon":131.605764,"city":"oita","source":"osm","changingTable":false,"wheelchair":false,"fee":false},{"id":"osm-node-2103429096","lat":33.231166,"lon":131.655454,"city":"oita","source":"osm","changingTable":false,"wheelchair":false,"fee":false},{"id":"osm-node-2128763761","lat":33.233683,"lon":131.655994,"city":"oita","source":"osm","changingTable":false,"wheelchair":false,"fee":false},{"id":"osm-node-2141226348","lat":33.22972,"lon":131.655815,"city":"oita","source":"osm","changingTable":false,"wheelchair":false,"fee":false},{"id":"osm-node-3700717714","lat":33.255619,"lon":131.547023,"city":"oita","source":"osm","changingTable":false,"wheelchair":false,"fee":false},{"id":"osm-node-4944976551","lat":33.398566,"lon":131.565554,"city":"oita","source":"osm","changingTable":false,"wheelchair":false,"fee":false},{"id":"osm-node-5320274302","lat":33.232712,"lon":131.608507,"city":"oita","source":"osm","changingTable":false,"wheelchair":false,"fee":false},{"id":"osm-node-5322611240","lat":33.252311,"lon":131.679785,"city":"oita","source":"osm","changingTable":false,"wheelchair":false,"fee":false},{"id":"osm-node-5884726203","lat":33.232419,"lon":131.652647,"city":"oita","source":"osm","changingTable":false,"wheelchair":false,"fee":false},{"id":"osm-node-9681205248","lat":33.254143,"lon":131.718301,"city":"oita","source":"osm","changingTable":false,"wheelchair":false,"fee":false},{"id":"osm-node-10991141060","lat":33.314943,"lon":131.500771,"city":"oita","source":"osm","changingTable":false,"wheelchair":false,"fee":false},{"id":"osm-node-11237427482","lat":33.233196,"lon":131.749205,"city":"oita","source":"osm","changingTable":false,"wheelchair":false,"fee":false,"name":"公衆トイレ"},{"id":"osm-node-12304494388","lat":33.23283,"lon":131.607661,"city":"oita","source":"osm","changingTable":false,"wheelchair":true,"fee":false},{"id":"osm-node-12585316526","lat":33.246382,"lon":131.584751,"city":"oita","source":"osm","changingTable":false,"wheelchair":false,"fee":false},{"id":"osm-node-12900471117","lat":33.272272,"lon":131.50848,"city":"oita","source":"osm","changingTable":false,"wheelchair":false,"fee":false},{"id":"osm-node-13043430448","lat":33.27942,"lon":131.500088,"city":"oita","source":"osm","changingTable":false,"wheelchair":false,"fee":false,"name":"別府駅構内トイレ"},{"id":"osm-node-13043430449","lat":33.279913,"lon":131.500453,"city":"oita","source":"osm","changingTable":false,"wheelchair":false,"fee":false,"name":"別府1番街トイレ"},{"id":"osm-node-13109451863","lat":33.238529,"lon":131.611472,"city":"oita","source":"osm","changingTable":false,"wheelchair":false,"fee":false},{"id":"osm-node-13166687419","lat":33.196722,"lon":131.513904,"city":"oita","source":"osm","changingTable":false,"wheelchair":false,"fee":false},{"id":"osm-node-13261418884","lat":33.209118,"lon":131.655152,"city":"oita","source":"osm","changingTable":false,"wheelchair":false,"fee":false},{"id":"osm-node-13261425925","lat":33.213399,"lon":131.65638,"city":"oita","source":"osm","changingTable":false,"wheelchair":false,"fee":false},{"id":"osm-node-13380020996","lat":33.241669,"lon":131.595815,"city":"oita","source":"osm","changingTable":false,"wheelchair":false,"fee":false},{"id":"osm-node-13420457898","lat":33.239147,"lon":131.593345,"city":"oita","source":"osm","changingTable":false,"wheelchair":false,"fee":false},{"id":"osm-way-193164227","lat":33.222297,"lon":131.654467,"city":"oita","source":"osm","changingTable":false,"wheelchair":false,"fee":false},{"id":"osm-way-193164258","lat":33.220977,"lon":131.658099,"city":"oita","source":"osm","changingTable":false,"wheelchair":false,"fee":false},{"id":"osm-way-193164513","lat":33.225215,"lon":131.653363,"city":"oita","source":"osm","changingTable":false,"wheelchair":false,"fee":false},{"id":"osm-way-200352986","lat":33.232367,"lon":131.65765,"city":"oita","source":"osm","changingTable":false,"wheelchair":false,"fee":false},{"id":"osm-way-204105725","lat":33.228485,"lon":131.655603,"city":"oita","source":"osm","changingTable":false,"wheelchair":true,"fee":false},{"id":"osm-way-400238526","lat":33.239811,"lon":131.611643,"city":"oita","source":"osm","changingTable":false,"wheelchair":false,"fee":false},{"id":"osm-way-411827326","lat":33.278222,"lon":131.507104,"city":"oita","source":"osm","changingTable":false,"wheelchair":true,"fee":false,"name":"公衆トイレ (北浜公園)"},{"id":"osm-way-412636611","lat":33.285652,"lon":131.504813,"city":"oita","source":"osm","changingTable":false,"wheelchair":false,"fee":false},{"id":"osm-way-412636613","lat":33.282629,"lon":131.505848,"city":"oita","source":"osm","changingTable":false,"wheelchair":false,"fee":false},{"id":"osm-way-412909756","lat":33.297148,"lon":131.503426,"city":"oita","source":"osm","changingTable":false,"wheelchair":true,"fee":false},{"id":"osm-way-413408208","lat":33.236934,"lon":131.605187,"city":"oita","source":"osm","changingTable":false,"wheelchair":false,"fee":false},{"id":"osm-way-413505014","lat":33.264275,"lon":131.508103,"city":"oita","source":"osm","changingTable":false,"wheelchair":false,"fee":false},{"id":"osm-way-413974182","lat":33.290914,"lon":131.504368,"city":"oita","source":"osm","changingTable":false,"wheelchair":false,"fee":false},{"id":"osm-way-413991518","lat":33.273339,"lon":131.507855,"city":"oita","source":"osm","changingTable":false,"wheelchair":false,"fee":false,"name":"公衆トイレ（仲良公園）","nameEn":"Public Toilet (Nakayoshi Park)"},{"id":"osm-way-421793503","lat":33.275797,"lon":131.505144,"city":"oita","source":"osm","changingTable":false,"wheelchair":false,"fee":false,"name":"ポケットパーク公衆トイレ","nameEn":"Pocket Park Public Toilet"},{"id":"osm-way-498037656","lat":33.195716,"lon":131.55445,"city":"oita","source":"osm","changingTable":false,"wheelchair":false,"fee":false},{"id":"osm-way-498037657","lat":33.195137,"lon":131.552407,"city":"oita","source":"osm","changingTable":false,"wheelchair":false,"fee":false},{"id":"osm-way-500297405","lat":33.180295,"lon":131.574461,"city":"oita","source":"osm","changingTable":false,"wheelchair":false,"fee":false},{"id":"osm-way-506175844","lat":33.200374,"lon":131.650064,"city":"oita","source":"osm","changingTable":false,"wheelchair":false,"fee":false},{"id":"osm-way-506175845","lat":33.201924,"lon":131.654846,"city":"oita","source":"osm","changingTable":false,"wheelchair":false,"fee":false},{"id":"osm-way-565043299","lat":33.373242,"lon":131.530331,"city":"oita","source":"osm","changingTable":false,"wheelchair":false,"fee":false},{"id":"osm-way-565046761","lat":33.366317,"lon":131.531858,"city":"oita","source":"osm","changingTable":false,"wheelchair":false,"fee":false},{"id":"osm-way-565060669","lat":33.376023,"lon":131.530638,"city":"oita","source":"osm","changingTable":false,"wheelchair":false,"fee":false},{"id":"osm-way-565069635","lat":33.375255,"lon":131.524092,"city":"oita","source":"osm","changingTable":false,"wheelchair":false,"fee":false},{"id":"osm-way-565069638","lat":33.376093,"lon":131.519449,"city":"oita","source":"osm","changingTable":false,"wheelchair":false,"fee":false},{"id":"osm-way-565069639","lat":33.377467,"lon":131.519393,"city":"oita","source":"osm","changingTable":false,"wheelchair":false,"fee":false},{"id":"osm-way-566001700","lat":33.367759,"lon":131.525865,"city":"oita","source":"osm","changingTable":false,"wheelchair":false,"fee":false},{"id":"osm-way-593734375","lat":33.239535,"lon":131.612916,"city":"oita","source":"osm","changingTable":false,"wheelchair":true,"fee":false},{"id":"osm-way-609670231","lat":33.203363,"lon":131.652058,"city":"oita","source":"osm","changingTable":false,"wheelchair":false,"fee":false},{"id":"osm-way-675154177","lat":33.202188,"lon":131.658766,"city":"oita","source":"osm","changingTable":false,"wheelchair":false,"fee":false},{"id":"osm-way-740046817","lat":33.250201,"lon":131.604695,"city":"oita","source":"osm","changingTable":false,"wheelchair":false,"fee":false},{"id":"osm-way-757487704","lat":33.190146,"lon":131.703003,"city":"oita","source":"osm","changingTable":false,"wheelchair":false,"fee":false},{"id":"osm-way-757538234","lat":33.191894,"lon":131.701496,"city":"oita","source":"osm","changingTable":false,"wheelchair":false,"fee":false},{"id":"osm-way-758841673","lat":33.214424,"lon":131.649419,"city":"oita","source":"osm","changingTable":false,"wheelchair":false,"fee":false},{"id":"osm-way-758865015","lat":33.244943,"lon":131.629754,"city":"oita","source":"osm","changingTable":false,"wheelchair":false,"fee":false},{"id":"osm-way-759143042","lat":33.237699,"lon":131.636669,"city":"oita","source":"osm","changingTable":false,"wheelchair":false,"fee":false},{"id":"osm-way-759147646","lat":33.242154,"lon":131.625905,"city":"oita","source":"osm","changingTable":false,"wheelchair":false,"fee":false},{"id":"osm-way-761246517","lat":33.239914,"lon":131.599945,"city":"oita","source":"osm","changingTable":false,"wheelchair":false,"fee":false},{"id":"osm-way-855722888","lat":33.235506,"lon":131.607952,"city":"oita","source":"osm","changingTable":false,"wheelchair":true,"fee":false},{"id":"osm-way-890228467","lat":33.189037,"lon":131.597519,"city":"oita","source":"osm","changingTable":false,"wheelchair":false,"fee":false},{"id":"osm-way-947220307","lat":33.181316,"lon":131.595689,"city":"oita","source":"osm","changingTable":false,"wheelchair":false,"fee":false},{"id":"osm-way-950018783","lat":33.184859,"lon":131.601086,"city":"oita","source":"osm","changingTable":false,"wheelchair":false,"fee":false},{"id":"osm-way-952638453","lat":33.253526,"lon":131.720746,"city":"oita","source":"osm","changingTable":false,"wheelchair":false,"fee":false},{"id":"osm-way-952638463","lat":33.247792,"lon":131.721022,"city":"oita","source":"osm","changingTable":false,"wheelchair":false,"fee":false},{"id":"osm-way-953330659","lat":33.24504,"lon":131.739693,"city":"oita","source":"osm","changingTable":false,"wheelchair":false,"fee":false},{"id":"osm-way-954203848","lat":33.245376,"lon":131.73886,"city":"oita","source":"osm","changingTable":false,"wheelchair":false,"fee":false},{"id":"osm-way-954523917","lat":33.240272,"lon":131.604648,"city":"oita","source":"osm","changingTable":false,"wheelchair":false,"fee":false},{"id":"osm-way-955763568","lat":33.245779,"lon":131.63699,"city":"oita","source":"osm","changingTable":false,"wheelchair":false,"fee":false},{"id":"osm-way-955763569","lat":33.243748,"lon":131.636357,"city":"oita","source":"osm","changingTable":false,"wheelchair":false,"fee":false},{"id":"osm-way-955763584","lat":33.244796,"lon":131.636142,"city":"oita","source":"osm","changingTable":false,"wheelchair":false,"fee":false},{"id":"osm-way-955763586","lat":33.248739,"lon":131.636878,"city":"oita","source":"osm","changingTable":false,"wheelchair":false,"fee":false},{"id":"osm-way-955763591","lat":33.24794,"lon":131.636225,"city":"oita","source":"osm","changingTable":false,"wheelchair":false,"fee":false},{"id":"osm-way-955763594","lat":33.246102,"lon":131.635932,"city":"oita","source":"osm","changingTable":false,"wheelchair":false,"fee":false},{"id":"osm-way-955763601","lat":33.251182,"lon":131.628976,"city":"oita","source":"osm","changingTable":false,"wheelchair":true,"fee":false},{"id":"osm-way-957868797","lat":33.243692,"lon":131.706066,"city":"oita","source":"osm","changingTable":false,"wheelchair":false,"fee":false},{"id":"osm-way-957868799","lat":33.250176,"lon":131.7167,"city":"oita","source":"osm","changingTable":false,"wheelchair":false,"fee":false},{"id":"osm-way-958442210","lat":33.251813,"lon":131.725439,"city":"oita","source":"osm","changingTable":false,"wheelchair":false,"fee":false},{"id":"osm-way-959611283","lat":33.24612,"lon":131.718768,"city":"oita","source":"osm","changingTable":false,"wheelchair":false,"fee":false},{"id":"osm-way-960063683","lat":33.242274,"lon":131.692961,"city":"oita","source":"osm","changingTable":false,"wheelchair":false,"fee":false},{"id":"osm-way-964561159","lat":33.259555,"lon":131.693693,"city":"oita","source":"osm","changingTable":false,"wheelchair":false,"fee":false},{"id":"osm-way-964561165","lat":33.258159,"lon":131.695055,"city":"oita","source":"osm","changingTable":false,"wheelchair":false,"fee":false},{"id":"osm-way-964669688","lat":33.226459,"lon":131.748843,"city":"oita","source":"osm","changingTable":false,"wheelchair":false,"fee":false},{"id":"osm-way-966642606","lat":33.226455,"lon":131.637313,"city":"oita","source":"osm","changingTable":false,"wheelchair":false,"fee":false},{"id":"osm-way-973456715","lat":33.228427,"lon":131.579441,"city":"oita","source":"osm","changingTable":false,"wheelchair":false,"fee":false},{"id":"osm-way-985700800","lat":33.189211,"lon":131.608224,"city":"oita","source":"osm","changingTable":false,"wheelchair":false,"fee":false},{"id":"osm-way-986643593","lat":33.192926,"lon":131.620073,"city":"oita","source":"osm","changingTable":false,"wheelchair":false,"fee":false},{"id":"osm-way-1005181209","lat":33.238035,"lon":131.550469,"city":"oita","source":"osm","changingTable":false,"wheelchair":false,"fee":false},{"id":"osm-way-1080277856","lat":33.198308,"lon":131.665189,"city":"oita","source":"osm","changingTable":false,"wheelchair":false,"fee":false},{"id":"osm-way-1080277858","lat":33.197067,"lon":131.665592,"city":"oita","source":"osm","changingTable":false,"wheelchair":false,"fee":false},{"id":"osm-way-1130781589","lat":33.205457,"lon":131.647848,"city":"oita","source":"osm","changingTable":false,"wheelchair":false,"fee":false},{"id":"osm-way-1157622668","lat":33.231914,"lon":131.591396,"city":"oita","source":"osm","changingTable":false,"wheelchair":false,"fee":false},{"id":"osm-way-1157622673","lat":33.231918,"lon":131.593247,"city":"oita","source":"osm","changingTable":false,"wheelchair":false,"fee":false},{"id":"osm-way-1157622674","lat":33.234667,"lon":131.592627,"city":"oita","source":"osm","changingTable":false,"wheelchair":false,"fee":false},{"id":"osm-way-1183565436","lat":33.309075,"lon":131.502275,"city":"oita","source":"osm","changingTable":false,"wheelchair":true,"fee":false},{"id":"osm-way-1243794721","lat":33.369231,"lon":131.532146,"city":"oita","source":"osm","changingTable":false,"wheelchair":false,"fee":false},{"id":"osm-way-1308758323","lat":33.25626,"lon":131.555053,"city":"oita","source":"osm","changingTable":false,"wheelchair":false,"fee":false},{"id":"osm-way-1381677196","lat":33.291469,"lon":131.502115,"city":"oita","source":"osm","changingTable":false,"wheelchair":false,"fee":false,"name":"公衆トイレ（餅ヶ浜公園）","nameEn":"Public toilet (Mochigahama Park)"},{"id":"osm-way-1383354944","lat":33.27999,"lon":131.503289,"city":"oita","source":"osm","changingTable":false,"wheelchair":true,"fee":false},{"id":"osm-way-1388387885","lat":33.277493,"lon":131.504653,"city":"oita","source":"osm","changingTable":false,"wheelchair":false,"fee":false,"name":"まちなか交流館公衆トイレ","nameEn":"Machinaka Exchange Hall Public Toilet"},{"id":"osm-way-1408895875","lat":33.272743,"lon":131.505911,"city":"oita","source":"osm","changingTable":false,"wheelchair":false,"fee":false,"name":"松原公園 公衆トイレ","nameEn":"Matsubara Park Public Toilet"},{"id":"osm-way-1420004057","lat":33.269678,"lon":131.510476,"city":"oita","source":"osm","changingTable":false,"wheelchair":false,"fee":false,"name":"公衆トイレ（浜脇公園）","nameEn":"Hamawaki Park Public Toilet"},{"id":"osm-way-1420278011","lat":33.267794,"lon":131.510801,"city":"oita","source":"osm","changingTable":false,"wheelchair":false,"fee":false},{"id":"osm-way-1421310436","lat":33.183136,"lon":131.576195,"city":"oita","source":"osm","changingTable":false,"wheelchair":false,"fee":false},{"id":"osm-way-1451036058","lat":33.208948,"lon":131.601512,"city":"oita","source":"osm","changingTable":false,"wheelchair":true,"fee":false}]